odoo/addons/product_pricelist_show_product_ref/README.rst
odoo/addons/product_pricelist_show_product_ref/__init__.py
odoo/addons/product_pricelist_show_product_ref/__manifest__.py
odoo/addons/product_pricelist_show_product_ref/i18n/product_pricelist_show_product_ref.pot
odoo/addons/product_pricelist_show_product_ref/models/__init__.py
odoo/addons/product_pricelist_show_product_ref/models/product_pricelist.py
odoo/addons/product_pricelist_show_product_ref/readme/CONFIGURE.rst
odoo/addons/product_pricelist_show_product_ref/readme/CONTRIBUTORS.rst
odoo/addons/product_pricelist_show_product_ref/readme/DESCRIPTION.rst
odoo/addons/product_pricelist_show_product_ref/readme/USAGE.rst
odoo/addons/product_pricelist_show_product_ref/static/description/icon.png
odoo/addons/product_pricelist_show_product_ref/static/description/index.html
odoo/addons/product_pricelist_show_product_ref/tests/__init__.py
odoo/addons/product_pricelist_show_product_ref/tests/test_product_pricelist_show_product_ref.py
odoo12_addon_product_pricelist_show_product_ref-12.0.2.0.1.dist-info/METADATA
odoo12_addon_product_pricelist_show_product_ref-12.0.2.0.1.dist-info/WHEEL
odoo12_addon_product_pricelist_show_product_ref-12.0.2.0.1.dist-info/top_level.txt
odoo12_addon_product_pricelist_show_product_ref-12.0.2.0.1.dist-info/RECORD
